sendevent_touch/LICENSE
sendevent_touch/README.MD
sendevent_touch/__init__.py
sendevent_touch/requirements.txt
sendevent_touch/thirdparty.json
sendevent_touch-0.11.dist-info/LICENSE.rst
sendevent_touch-0.11.dist-info/METADATA
sendevent_touch-0.11.dist-info/WHEEL
sendevent_touch-0.11.dist-info/top_level.txt
sendevent_touch-0.11.dist-info/RECORD
